curlydl/__init__.py
curlydl/download_manager.py
curlydl/engine.py
curlydl/error_handler.py
curlydl/examples/advanced_download.py
curlydl/examples/async_download.py
curlydl/examples/basic_download.py
curlydl/filesystem.py
curlydl/metadata/__init__.py
curlydl/metadata/exceptions.py
curlydl/metadata/manager.py
curlydl/metadata/models.py
curlydl/metadata/storage.py
curlydl/tests/test_download.py
curlydl/tests/test_engine.py
curlydl/tests/test_error_handler.py
curlydl/tests/test_filesystem.py
curlydl/tests/test_metadata.py
curlydl-0.2.1.dist-info/METADATA
curlydl-0.2.1.dist-info/WHEEL
curlydl-0.2.1.dist-info/RECORD
