Metadata-Version: 2.1
Name: curlydl
Version: 0.2.1
Summary: A Python Download Manager SDK using libcurl
Home-page: https://github.com/hamedkazemi/CurlyDL
Author: Hamed Kazemi
Author-email: kafa1942@gmail.com
Requires-Python: >=3.7,<4.0
Classifier: Programming Language :: Python :: 3
Classifier: Programming Language :: Python :: 3.7
Classifier: Programming Language :: Python :: 3.8
Classifier: Programming Language :: Python :: 3.9
Classifier: Programming Language :: Python :: 3.10
Classifier: Programming Language :: Python :: 3.11
Classifier: Programming Language :: Python :: 3.12
Requires-Dist: certifi (>=2024.8.30,<2025.0.0)
Requires-Dist: psutil (>=6.1.0,<7.0.0)
Requires-Dist: pycurl (>=7.45.0,<8.0.0)
Requires-Dist: tqdm (>=4.66.6,<5.0.0)
Project-URL: Repository, https://github.com/hamedkazemi/CurlyDL
